airflow_pydantic_dags/__init__.py
airflow_pydantic_dags/dag.py
airflow_pydantic_dags/exceptions.py
airflow_pydantic_dags/warnings.py
airflow_pydantic_dags/examples/__init__.py
airflow_pydantic_dags/examples/example_dag.py
airflow_pydantic_dags-1.0.0.dist-info/LICENSE
airflow_pydantic_dags-1.0.0.dist-info/METADATA
airflow_pydantic_dags-1.0.0.dist-info/WHEEL
airflow_pydantic_dags-1.0.0.dist-info/top_level.txt
airflow_pydantic_dags-1.0.0.dist-info/RECORD
