Metadata-Version: 2.1
Name: airflow-pydantic-dags
Version: 1.0.0
Summary: DAG subclass that parses run params (and config) using pydantic, and makes it available as a pydantic object in Tasks
Author-email: Alex Seeholzer <seeholzer@gmail.com>
License: BSD-3-Clause
Keywords: airflow,pydantic
Classifier: Framework :: Apache Airflow
Classifier: Programming Language :: Python :: 3
Requires-Python: >=3.9
License-File: LICENSE
Requires-Dist: apache-airflow <=2.7,>=2.6
Requires-Dist: pydantic <2,>=1.10
